README.md
setup.py
Lotlan_Scheduler.egg-info/PKG-INFO
Lotlan_Scheduler.egg-info/SOURCES.txt
Lotlan_Scheduler.egg-info/dependency_links.txt
Lotlan_Scheduler.egg-info/requires.txt
Lotlan_Scheduler.egg-info/top_level.txt
lotlan_scheduler/__init__.py
lotlan_scheduler/defines.py
lotlan_scheduler/demo.py
lotlan_scheduler/helpers.py
lotlan_scheduler/scheduler.py
lotlan_scheduler/api/__init__.py
lotlan_scheduler/api/event.py
lotlan_scheduler/api/location.py
lotlan_scheduler/api/materialflow.py
lotlan_scheduler/api/transportorder.py
lotlan_scheduler/api/transportorder_step.py
lotlan_scheduler/logger/__init__.py
lotlan_scheduler/logger/sqlite_logger.py
lotlan_scheduler/model/__init__.py
lotlan_scheduler/model/transport/__init__.py
lotlan_scheduler/model/transport/instance.py
lotlan_scheduler/model/transport/task.py
lotlan_scheduler/model/transport/template.py
lotlan_scheduler/model/transport/transport.py
lotlan_scheduler/parser/LoTLanLexer.py
lotlan_scheduler/parser/LoTLanParser.py
lotlan_scheduler/parser/LoTLanParserListener.py
lotlan_scheduler/parser/LoTLanParserVisitor.py
lotlan_scheduler/parser/__init__.py
lotlan_scheduler/parser/lotlan_tree_visitor.py
lotlan_scheduler/petri_net/__init__.py
lotlan_scheduler/petri_net/drawer.py
lotlan_scheduler/petri_net/generator.py
lotlan_scheduler/petri_net/logic.py
lotlan_scheduler/validation/__init__.py
lotlan_scheduler/validation/semantic_validator.py
lotlan_scheduler/validation/syntax_error_listener.py
lotlan_scheduler/validation/task_language.py
lotlan_scheduler/validation/task_language_test.py