Metadata-Version: 2.1
Name: Lotlan-Scheduler
Version: 1.1.0
Summary: Scheduler for tasks generated from Lotlan files
Home-page: UNKNOWN
Author: Peter Detzner, Maximilian Hörstrup
License: UNKNOWN
Platform: UNKNOWN
Classifier: Programming Language :: Python :: 3
Classifier: License :: OSI Approved :: Apache Software License
Classifier: Operating System :: OS Independent
Requires-Python: >=3.6
